Lib_mechsolids_abhinav/Beam.py
Lib_mechsolids_abhinav/__init__.py
Lib_mechsolids_abhinav/math_functions.py
Lib_mechsolids_abhinav-0.0.1.dist-info/LICENSE
Lib_mechsolids_abhinav-0.0.1.dist-info/METADATA
Lib_mechsolids_abhinav-0.0.1.dist-info/WHEEL
Lib_mechsolids_abhinav-0.0.1.dist-info/top_level.txt
Lib_mechsolids_abhinav-0.0.1.dist-info/RECORD
