Metadata-Version: 2.1
Name: Lib_mechsolids_abhinav
Version: 0.0.1
Summary: Mechsolids Library for plotting SFD and BMD
Author-email: Abhinav Cillanki <abhinavcillanki@gmail.com>
Classifier: Programming Language :: Python :: 3
Classifier: License :: OSI Approved :: MIT License
Classifier: Operating System :: OS Independent
Requires-Python: >=3.7
License-File: LICENSE
